pyochain/__init__.py
pyochain/_dict.py
pyochain/_iter.py
pyochain/_tools.pyi
pyochain/_types.py
pyochain/py.typed
pyochain/rs.cpython-313-aarch64-linux-gnu.so
pyochain/rs.pyi
pyochain/traits/__init__.py
pyochain/traits/_iterable.py
pyochain-0.9.2.dist-info/METADATA
pyochain-0.9.2.dist-info/WHEEL
pyochain-0.9.2.dist-info/licenses/LICENSE.md
pyochain-0.9.2.dist-info/RECORD
