Metadata-Version: 2.4
Name: pyochain
Version: 0.9.2
Classifier: License :: OSI Approved :: MIT License
Requires-Dist: cytoolz>=1.0.1
License-File: LICENSE.md
Summary: Method chaining for iterables and dictionaries in Python.
Requires-Python: >=3.13
